[
	{
		"fileName": "1.jpg",
		"title": "pretty pictures",
		"description": "游戏美图pretty pictures"
	},
	{
		"fileName": "2.jpg",
		"title": "pretty pictures",
		"description": "游戏美图pretty pictures"
	},
	{
		"fileName": "3.jpg",
		"title": "pretty pictures",
		"description": "游戏美图pretty pictures"
	},
	{
		"fileName": "4.jpg",
		"title": "pretty pictures",
		"description": "游戏美图pretty pictures"
	},
	{
		"fileName": "5.jpg",
		"title": "pretty pictures",
		"description": "游戏美图pretty pictures"
	},
	{
		"fileName": "6.jpg",
		"title": "pretty pictures",
		"description": "游戏美图pretty pictures"
	},
	{
		"fileName": "7.jpg",
		"title": "pretty pictures",
		"description": "游戏美图pretty pictures"
	},
	{
		"fileName": "8.jpg",
		"title": "pretty pictures",
		"description": "游戏美图pretty pictures"
	},
	{
		"fileName": "9.jpg",
		"title": "pretty pictures",
		"description": "游戏美图pretty pictures"
	},
	{
		"fileName": "10.jpg",
		"title": "pretty pictures",
		"description": "游戏美图pretty pictures"
	},
	{
		"fileName": "11.jpg",
		"title": "pretty pictures",
		"description": "游戏美图pretty pictures"
	},
	{
		"fileName": "12.jpg",
		"title": "pretty pictures",
		"description": "游戏美图pretty pictures"
	},
	{
		"fileName": "13.jpg",
		"title": "pretty pictures",
		"description": "游戏美图pretty pictures"
	},
	{
		"fileName": "14.jpg",
		"title": "pretty pictures",
		"description": "游戏美图pretty pictures"
	}
]